pspdfkit/__init__.py
pspdfkit/api.py
py_pspdfkit-0.2.5.dist-info/LICENSE.md
py_pspdfkit-0.2.5.dist-info/METADATA
py_pspdfkit-0.2.5.dist-info/WHEEL
py_pspdfkit-0.2.5.dist-info/top_level.txt
py_pspdfkit-0.2.5.dist-info/zip-safe
py_pspdfkit-0.2.5.dist-info/RECORD
