Metadata-Version: 2.1
Name: py-pspdfkit
Version: 0.2.5
Summary: A simple API wrapper for PSPDFKit
Home-page: https://github.com/tizz98/py-pspdfkit
Author: Elijah Wilson
Author-email: elijah@elijahwilson.me
License: MIT
Download-URL: https://github.com/tizz98/py-pspdfkit/tarball/0.2.5
Keywords: pspdfkit pdf
Platform: UNKNOWN
Classifier: Intended Audience :: Developers
Classifier: Topic :: Software Development :: Libraries
Classifier: License :: OSI Approved :: MIT License
Classifier: Programming Language :: Python :: 3
Classifier: Programming Language :: Python :: 3.3
Classifier: Programming Language :: Python :: 3.4
Requires-Dist: requests (<3.0,>=2.22)
